{"format":1,"version":"4.5.2","settings":"89af03073c96e5b8953d468af471e5f8","files":{"lektor_cli_py":{"hash":"e88c3d0891653208f102e5e9ef9cc754","index":{"nums":[1,338,0,112,112,23,59],"html_filename":"lektor_cli_py.html","relative_filename":"lektor/cli.py"}},"lektor_imagetools_py":{"hash":"08c72cc557e6dd1c26bcd494ee28bbfd","index":{"nums":[1,335,0,53,116,29,39],"html_filename":"lektor_imagetools_py.html","relative_filename":"lektor/imagetools.py"}},"lektor_metaformat_py":{"hash":"6bee112162bdd050f38c7b1f418e9826","index":{"nums":[1,71,0,7,50,5,9],"html_filename":"lektor_metaformat_py.html","relative_filename":"lektor/metaformat.py"}},"lektor_sourcesearch_py":{"hash":"b815e1098d3e32ab0669f7405670fc03","index":{"nums":[1,80,0,40,38,4,28],"html_filename":"lektor_sourcesearch_py.html","relative_filename":"lektor/sourcesearch.py"}},"lektor_types_flow_py":{"hash":"5cda51d3cb534a5e8e96235aaf854ec6","index":{"nums":[1,143,0,30,61,13,24],"html_filename":"lektor_types_flow_py.html","relative_filename":"lektor/types/flow.py"}},"lektor_utils_py":{"hash":"70766533b4d6a26aac8dbb6248edc99b","index":{"nums":[1,499,0,172,231,28,102],"html_filename":"lektor_utils_py.html","relative_filename":"lektor/utils.py"}}}}